MANIFEST.in
README.txt
setup.cfg
setup.py
metascapes/__init__.py
metascapes.web2cache.egg-info/PKG-INFO
metascapes.web2cache.egg-info/SOURCES.txt
metascapes.web2cache.egg-info/dependency_links.txt
metascapes.web2cache.egg-info/entry_points.txt
metascapes.web2cache.egg-info/namespace_packages.txt
metascapes.web2cache.egg-info/paster_plugins.txt
metascapes.web2cache.egg-info/requires.txt
metascapes.web2cache.egg-info/top_level.txt
metascapes.web2cache.egg-info/zip-safe
metascapes/web2cache/README.txt
metascapes/web2cache/__init__.py
metascapes/web2cache/config.py
metascapes/web2cache/configure.zcml
metascapes/web2cache/setuphandlers.py
metascapes/web2cache/tool.gif
metascapes/web2cache/browser/__init__.py
metascapes/web2cache/browser/__init__.pyo
metascapes/web2cache/browser/configure.zcml
metascapes/web2cache/browser/controlpanel.py
metascapes/web2cache/browser/images/__init__.py
metascapes/web2cache/browser/images/tool.png
metascapes/web2cache/content/__init__.py
metascapes/web2cache/content/__init__.pyo
metascapes/web2cache/content/configure.zcml
metascapes/web2cache/interfaces/__init__.py
metascapes/web2cache/interfaces/__init__.pyo
metascapes/web2cache/interfaces/utility.py
metascapes/web2cache/portlets/__init__.py
metascapes/web2cache/portlets/__init__.pyo
metascapes/web2cache/portlets/configure.zcml
metascapes/web2cache/profiles/default/controlpanel.xml
metascapes/web2cache/profiles/default/factorytool.xml
metascapes/web2cache/profiles/default/metadata.xml
metascapes/web2cache/profiles/default/toolset.xml
metascapes/web2cache/profiles/default/types.xml
metascapes/web2cache/profiles/default/web2cache_marker.txt
metascapes/web2cache/tests/__init__.py
metascapes/web2cache/tests/__init__.pyo
metascapes/web2cache/tests/base.py
metascapes/web2cache/tests/test_doctest.py
metascapes/web2cache/tools/MetascapesWeb2Tool.py
metascapes/web2cache/tools/__init__.py