Metadata-Version: 1.0
Name: metascapes.web2cache
Version: 0.2
Summary: An indexable web2.0 cache
Home-page: http://svn.plone.org/svn/collective/
Author: Bernhard Snizek
Author-email: bs@metascapes.org
License: GPL
Keywords: web2 cache index easy
Platform: UNKNOWN
Classifier: Framework :: Plone
Classifier: Intended Audience :: Developers
Classifier: License :: OSI Approved :: GNU General Public License (GPL)
